{
    "volume_title": "浄霊・神示の健康法・自然農法編",
    "themes": [
        {
            "topics": [
                {
                    "title": "風邪と結核　３",
                    "date": "昭和11年6月10日",
                    "content": "<b><font size=\"+2\">明主様御教え　「医学は退歩したか」</font></b>　（昭和11年6月10日御執筆）<br/>\n<br/>「去る五月下旬の朝日紙上に、こういう事が掲載してあった。<br><br>\n<b><font color=\"#0000ff\" size=\"+1\">新聞記事</font></b><br/>「非常時局の中堅層をなす我が壮丁（そうてい）の体格及び健康が近年次第に低下しつつあるので当局では深く憂慮し、<br/>\n<br/>二十七日午後三時から九段偕行社に陸軍側から小泉医務局長、中島二等軍医正、園田一等軍医、文部省側から岩原体育課長、大西学校衛生官、伊藤事務官が出席、対策協議する事となった。<br/>\n<br/>こう云う陸軍、文部両当局の協議は今度初めての企（くわだ）てである。<br/>\n<br/>我国壮丁の体格は筋骨の弱い丙種、丁種の者が大正十一年から十五年までは千人に対し二百五十人であったのに、昭和七年度は千人に対し三百五十人に増し、翌八年は更にこの兵役免除者が四百人に増加している。<br/>\n<br/>又壮丁の胸部疾患も明治三十二年には百人中二人だったのが、現在ではこの十倍、即ち百人中二十人に増率し、身長に比して体重の増加は著しく劣って居り、教育程度が進むにつれて体格は悪く丙種丁種が多いという悲しむべき状態である。<br/>\n<br/>この壮丁の悲況を陸軍、文部両当局の協議がいかに打開するか、各方面から注目されている。」（新聞記事は以上）<br><br>\n<br/>「右のごとき、明治三十二年から三十数年を経た今日、兵役不能者が十倍にもなったという事は実に驚くべきである。<br/>\n<br/>国家的に観てこれ以上の重大問題が他にあるであろうか。<br/>\n<br/>須（すべか）らく国家全体の智嚢を搾（しぼ）って、その原因を検討しなければならないのである。<br/>\n<br/>しかも一方医学は非常に進歩したという事になって安心して居るにも不拘（かかわらず）、<br/>\n<br/>事実は反対にそれを裏切っているのはいかなる原因に拠（よ）るのであるか。<br/>\n<br/>この趨勢を以てすれば、今後といえども殖えるとも減少する見込はないと想えるのである。<br/>\n<br/>何となればその根本原因が適確に判明されて、それに対する方策が確立されなければである。<br/>\n<br/>しかるにこの重大事に対して、当局も世人も案外無関心で居る、ただ一部の当局のみが焦慮しているに過ぎないとは、聖代におけるまことに不可解事であるといってもよい。<br/>\n<br/>この一事に徴してみるも、現代医学衛生における根本的欠陥がなければならない事である。<br/>\n<br/>故にこの重大事を救うの道は、この欠陥の発見で、それ以外には絶対無いと言えよう。<br/>\n<br/>しかるに私は、その欠陥を発見し得たので、発見と共に全く驚歎久しゅうしたのである。<br/>\n<br/>それは一体何であるか、以下詳細に述べてみよう。<br><br>これら激増しつつある虚弱者特に結核患者（弱体児童を含む）に対し、現代医療は何をして居るのであろうか。<br/>\n<br/>真に防止しつつあるのであろうかというに、実際は防止所ではなく反対にどしどし作っているという一大奇怪事である。<br/>\n<br/>そうしてこの様な信ずべからざる程の重大事に誰もが気が付かないという問題である。<br/>\n<br/>この意味において、むしろ医療なるものが無かったなら、兵役不能者は一大激減をするであろうとさえ思うのである。<br/>\n<br/>否事実そうである事は火を睹（み）るよりも瞭（あきら）かである。それは医学が進歩するに随って漸増するという一事が遺憾なく証拠立てている。<br/>\n<br/>千人中二百人にも兵役不能者が増加したという生きた事実こそ、私の右の説を裏書して余りあるのである。<br/>\n<br/>噫（ああ）、国家の前途に対して、これより大なるものは無いであろう。<br/>\n<br/>しからば右のごとき、医学の誤謬とは何であるか。それを赤裸々に述べなくてはならない。<br/>\n<br/>それを述べるに当って、その誤謬の根本とも言うべき病気の本体から明かにする必要があろう。<br/>\n<br/>そうして医学におけるそれの認識が一大錯覚に陥ってるという事実である。<br/>\n<br/>それは医学においては、何故に病気が発生するかという事には未だ不明であって、<br/>\n<br/>医学上における目下のそれはあらゆる病原が黴菌であるという他動的原因、即ち他原説である。<br/>\n<br/>しかし、これがそもそもの誤謬である。<br/>\n<br/>否、全然誤謬ではないが、実は一面の解決でしかない事である。<br><br>しかるに、私の研究によれば、病気の本体は実は人間自身の自然浄化作用である。<br/>\n<br/>即ち、自原説である。<br/>\n<br/>それは何か、人間が生存上、あらゆる原因に因って不断に汚濁が堆積するのであって、それが為に血液の不浄化となり、その不浄化が病原となるのである。<br/>\n<br/>が、それは不浄血液そのものではなくて、その不浄血液を浄化さすべき工作そのものである。<br/>\n<br/>故に、病気現象なるものは、浄化作用としての苦痛でしかないのである。<br/>\n<br/>そうして結核患者は何が故に発生するのかといえば、それは汚濁が不浄血及び膿汁となって、何人といえども、頸部付近と肩部付近に溜積するのである。<br/>\n<br/>そうして、その汚濁の溜積がある程度を越ゆる時、それの解消作用が起るのであって、その、動機促進が冬の寒冷でその工作が風邪である。<br/>\n<br/>故に、風邪に罹るや、それら汚濁を解溶すべく発熱が起り、膿は稀薄となるので、喀痰及び鼻汁とし排除されるので、それに依って人体は健康を保ってゆけるのである。<br/>\n<br/>故に風邪こそ実に、最簡便なる天与の万病離脱法である。<br/>\n<br/>しかるに昔から、風邪は万病の因などというが、これは全く誤りであって、<br/>\n<br/>実はその反対の万病を免れ得る最も最善の方法であって、実に創造神が作為されたいとも巧妙なる保健法である。<br/>\n<br/>にも不拘（かかわらず）、それに盲目である医学は、風邪に罹る事を非常に恐れ、飽くまでこれを避けんとするのである。<br/>\n<br/>それが為万が一罹病した時、発熱を懼（おそ）れて飽くまで下げようとするのである。<br/>\n<br/>その結果折角の浄化は不能となって、ついに汚濁はそのまま残存し、時日の経過と共に固結してしまうのである。<br/>\n<br/>この汚濁固結こそ、実に結核的弱体化のそもそもの原因である。<br/>\n<br/>そうして、頸部及び肩部付近に溜積せる水膿固結は、解熱剤、安静療法その他によって一旦解熱し、鎮静を得るといえども、それは一時的で真の治癒ではないから、<br/>\n<br/>再び自然浄化作用に因って風邪に罹るのであるが、医療は再び浄化防止を行うので、その結果として膿の固結は漸次加重されていく訳である。<br/>\n<br/>かくのごとき事を繰返すにおいて、膿の固結は益々増加するから、当然の結果として自然浄化に因る発熱は解熱剤を以てしても容易に鎮静しない程に執拗（しつよう）となるのである。<br/>\n<br/>その必要となった発熱の為に溶解した膿が喀痰となって排泄する。<br/>\n<br/>その為に咳嗽が起り、それが連続的となるのである。<br><br>又、今一つの症状を見逃す事は出来ない。<br/>\n<br/>それは、不断に頸腺及び肩部に集溜しようとしつつある全身の汚濁は、右の部に溜積した長時日の膿の固結に遭ってその部への集溜は不可能となるので、<br/>\n<br/>止むを得ずそれ以下である胸部の上辺から、乳及び腋の下の肋骨膜に溜積固着するのである。<br/>\n<br/>その固着部が乳及び腋の下辺である訳は、勿論、人間が両腕を絶えず使用するという、その為の神経集中によるからである。<br/>\n<br/>そうしてこの症状が胸部であるによって、医家の診断は肺結核又は肺浸潤とするのであるが、実はこの際は肺には何ら異状はないのである。<br/>\n<br/>何となれば、右は肋骨の内部症状ではなくて肋骨の外部であるからである。<br/>\n<br/>しかし、何分発熱とラッセルとレントゲン写真に雲状を顕すにおいて、肺患と誤診するのは無理もないのであるが、これは全く否である。<br/>\n<br/>故に、この症状は余の治療に依れば、一人の例外なく全治するに見ても、肺に異状のない事が明かであろう。<br><br>次に、肺患悪化の原因として、特に消化不良の一事である。<br/>\n<br/>そうして、この原因の大部分が謬（あやま）れる医療の為である事は言うまでもない。<br/>\n<br/>それは、肺患と知るや、医療は絶対安静を行うのである。<br/>\n<br/>この為運動不足による胃弱は著しいものであるのと、今一つは消化薬を服用させる事であるが、<br/>\n<br/>事実において胃を強め、食欲を増進させようとするその目的とは反対の結果となるのである。<br/>\n<br/>なぜなれば、一時は胃薬によって消化は旺盛となるが、日を経るに従い、胃自身の活動力は漸次衰退するのである。<br/>\n<br/>それは薬剤が消化してくれるから、胃は活動の必要がないから衰耗するのは当然な理である。<br/>\n<br/>その結果として、胃薬の効果が漸次薄弱化し、食欲不振となるから、いよいよ胃薬を服用させるという循環作用によって、<br/>\n<br/>胃はついに睡眠状態となるので、それが病勢を悪化さす事は、実に致命的でさえある。<br/>\n<br/>現在頗（すこぶ）る多数に上りつつあるという胃疾患の原因も、これで肯けるであろう。<br><br>その他、下痢、喀血、盗汗（ねあせ）等の原因及び療法等の誤謬も、右と大同小異であるから略する事とするが、<br/>\n<br/>要するに以上に依っても判明さるるごとく、現代医療は驚くべき錯覚の道を歩んでいるのである。<br/>\n<br/>これを一言にして言えば、人体に病気が発生するや、それを治癒しようとするその方法が治療の妨害となる事であって、<br/>\n<br/>特にその妨害の最も根本ともいうべきが解熱剤と氷冷である。<br/>\n<br/>故に、忌憚なく言えば、人体自身の治癒工作と治癒をさせまいとする医療との闘争で、その結果としての結核増加である。<br/>\n<br/>しからば、いかにすべきが最善であるかという事である。<br/>\n<br/>それはまず風邪に罹るや、発熱を尊重して、そのまま放置しておけばいいのである。<br/>\n<br/>そうすれば、汚濁は順調に解溶排泄さるるから根本的に頗る順調に治癒するので、勿論、再発の素因は消滅さるるのである。<br/>\n<br/>これは実験するにおいて一点の誤りの無い事を知るのである。<br/>\n<br/>この理によってみても、結核激増の真因は、全く解熱剤がその第一歩である事が知らるるであろう。<br/>\n<br/>故に、解熱剤禁止と氷冷法廃止と風邪非予防だけを行う事によっても、恐らく結核患者は三分の一以下に減少する事は断言してはばからないのである。<br/>\n<br/>実に、医学が結核患者を作りつつあるという、信ずべからざる程の戦慄事が、国家の保護の下に公然と行われつつあるという事である。<br/>\n<br/>しかしながら、医学においても、一部の進歩は認め得らるるのである。<br/>\n<br/>それは、機械の巧緻化と療法の複雑多岐と、薬剤の多種多用になった事である。<br/>\n<br/>しかしながら、根本である病原を錯覚している限り、それらはただ人々を幻惑させるに過ぎないのであって、<br/>\n<br/>反ってそれらに没頭し、満足しつつ終（つい）に根本に遠ざかってしまうという危険さえある事である。<br/>\n<br/>それ故に、病原の確定的発見さえあれば、器械や薬剤はむしろ不必要の存在でしかなくなるであろう。<br><br>次に、現在医家の診断に誤謬の多い事は、実に驚くべきものがある。<br/>\n<br/>余が診査するに、官立の大病院における診断でさえ、ほとんど七、八十パーセントは誤診である。<br/>\n<br/>これを読む人は信ずる事が出来得ないであろうが、事実は厳として動かす事が出来ないのである。<br/>\n<br/>それは医学において、唯一の診断法としているレントゲン写真でさえが、決して正確ではない事である。<br/>\n<br/>それは、前述の肋骨及びその外部に滞溜せる膿の固結と、未固結の膿汁のそれが、雲状に顕出するのを肺の疾患と誤る事によっても明かである。<br/>\n<br/>もっとも写真映像は平面であるからであろうが、これらも一大自覚の必要があるであろう。<br/>\n<br/>又、ラッセルにおいても、肺胞の場合もあるが、右の肋骨付近の水膿による場合も多いのである。<br/>\n<br/>又、肺胞にラッセルがあっても、肺患でない場合も多くある事を知らねばならない。<br/>\n<br/>又、微熱であるが、これはほとんど肺が原因であるのは十人に一人もない位である。<br/>\n<br/>そのほとんどは頸腺及び肩部、肋骨部、胃部、腹部、腰部等である。<br/>\n<br/>これらの発見に因る時、医学の診断の余りにも幼稚である事は不可解と思う程である。<br/>\n<br/>故に、現今、肺結核とされ、悲観している多数の患者は、実に肺に異常のない肺患者であると言ってもいいので、その事についていつも笑うのである。<br/>\n<br/>余が治療しつつある肺患の治病率は、その悉（ことごと）くがあらゆる医療を受けても治癒しないで、拗（こじ）れた難治症のみであるに不拘（かかわらず）、<br/>\n<br/>治癒実績が実に八十パーセント以上を挙げつつあるのは、何が故であるかといえば、肺に異常の無い、いわゆる肺患者であるからである。<br/>　<br/>\n<br/>次に、今一つの誤療を指摘してみよう。それは病気軽快と治癒との判別がなく、混同している事である。<br/>\n<br/>そもそも、病患とは前述のごとく、それは浄化作用であるから、発熱、咳嗽、喀痰、喀血、盗汗（ねあせ）等の種々の苦痛、<br/>\n<br/>それはその患者の活力が旺盛であればある程、苦痛現象が猛烈であるはずである。<br/>\n<br/>しかるにその場合、医療は苦痛緩和の為の対症療法を頻りに行うのである。<br/>\n<br/>その療法とは、薬剤と獣性滋養食及び絶対安静法等である。<br/>\n<br/>しかるに、前者は血液を溷濁（こんだく）させ、後者は全身的活力を衰耗させるのであるから、浄化力は薄弱化するのは当然である。<br/>\n<br/>その結果として熱は低下し、咳嗽も喀痰も減少するので、病症は確かに軽快し、治癒に向うごとく見ゆるので、時によりほとんど治癒されたかと思う事さえもある。<br/>\n<br/>が何ぞ知らん、これは浄化停止の為の一時的緩和であって治癒ではないから、再発か又は現状維持のまま、全治もせず悪化もしないで数年に及ぶのであって、この様な患者は頗る多い事は誰もが知るところである。<br/>\n<br/>これは全く自然治癒防止のそれであるから、この様な経過中において、患者が運動をすれば直ちに浄化力が発生するから発熱する。<br/>\n<br/>それを医家は驚いて病気悪化と誤解し中止させるのである。近来泰西において業務に従事しつつ結核治病をせよという説が現われたのは、この絶対安静の非に目覚めた証拠である。<br><br>以上のごとき、診断の不正確と病原の錯覚と治療法の誤謬等を綜合する時、現代医学なるものは一大革命をしない限り、国家の損失と民人の不幸は測り知れないであろう。<br/>\n<br/>この真相を徹底把握するにおいて、誰か寒心せざるものがあろうか。<br/>\n<br/>ここに吾人は一大警鐘を鳴らして、当事者に一大自覚を促さざるを得ないのである。<br/>\n<br/>表題の、「医学は退歩した乎」という事は、これに依て明かであると思うのである。」　（「新日本医術書」より） <hr/>\n<br/>\n<br/>",
                    "filename": "kaze3K.html",
                    "title_pt": "Resfriado e Tuberculose　３",
                    "content_pt": "<b><font size=\"+2\">Ensinamento de Meishu-Sama: \"A Medicina Retrocedeu?\"</font></b> (Escrito em 10 de junho de 1936)<br/>\n<br/>\"No final de maio passado, o jornal Asahi publicou o seguinte:<br><br>\n<b><font color=\"#0000ff\" size=\"+1\">Artigo de Jornal</font></b><br/>'Como o porte físico e a saúde dos nossos jovens em idade militar, que formam a camada central nesta situação de emergência, vêm declinando gradualmente nos últimos anos, as autoridades estão profundamente preocupadas e,<br/>\n<br/>no dia 27, a partir das 15 horas, no Kaikosha em Kudan, com a presença do Diretor do Departamento Médico Koizumi, do Cirurgião Militar de 2ª Classe Nakajima e do Cirurgião Militar de 1ª Classe Sonoda, por parte do Exército, e do Chefe da Seção de Educação Física Iwahara, do Oficial de Higiene Escolar Onishi e do Secretário Ito, por parte do Ministério da Educação, foi realizada uma reunião para discutir medidas.<br/>\n<br/>Esta é a primeira vez que se planeja uma reunião entre as autoridades do Exército e do Ministério da Educação.<br/>\n<br/>Quanto ao porte físico dos jovens do nosso país, os de categoria C e D, com músculos e ossos fracos, que eram 250 em cada mil entre 1922 e 1926, aumentaram para 350 em cada mil no ano de 1932, e no ano seguinte, 1933, o número de isentos do serviço militar aumentou ainda mais, para 400.<br/>\n<br/>Além disso, as doenças torácicas dos jovens, que eram de 2 em cada 100 em 1899, aumentaram atualmente para dez vezes mais, ou seja, 20 em cada 100; o aumento do peso em relação à altura é notavelmente inferior, e à medida que o nível educacional avança, o porte físico piora, havendo muitos de categoria C e D, o que é uma situação lamentável.<br/>\n<br/>Como a reunião entre as autoridades do Exército e do Ministério da Educação resolverá esta triste situação dos jovens é algo que está sendo observado por todos os setores.' (Fim do artigo de jornal)<br><br>\n<br/>\"Como visto acima, o fato de que, passados mais de trinta anos desde 1899, o número de inaptos para o serviço militar tenha aumentado dez vezes é realmente surpreendente.<br/>\n<br/>Do ponto de vista nacional, haverá outro problema mais grave do que este?<br/>\n<br/>Deve-se, sem dúvida, espremer a sabedoria de toda a nação para investigar a sua causa.<br/>\n<br/>Além disso, apesar de estarmos tranquilos por se dizer que a medicina progrediu muito,<br/>\n<br/>a que causa se deve o fato de a realidade trair isso de forma oposta?<br/>\n<br/>Com esta tendência, parece que no futuro não há perspectiva de diminuição, mas sim de aumento.<br/>\n<br/>Isso porque a sua causa fundamental não foi identificada com precisão e não foram estabelecidas medidas contra ela.<br/>\n<br/>No entanto, em relação a este assunto tão grave, as autoridades e o público em geral estão surpreendentemente indiferentes, e o fato de apenas uma parte das autoridades estar ansiosa pode ser considerado um fato verdadeiramente incompreensível nesta era sagrada.<br/>\n<br/>Apenas por este fato, deve haver uma falha fundamental na medicina e higiene modernas.<br/>\n<br/>Portanto, o caminho para salvar esta grave situação é a descoberta desta falha, e pode-se dizer que não há absolutamente nenhum outro.<br/>\n<br/>No entanto, eu consegui descobrir essa falha e, com a descoberta, fiquei maravilhado por muito tempo.<br/>\n<br/>O que é isso, afinal? Tentarei expor detalhadamente a seguir.<br><br>O que a medicina moderna está fazendo em relação a essas pessoas debilitadas que estão aumentando drasticamente, especialmente os pacientes com tuberculose (incluindo crianças debilitadas)?<br/>\n<br/>Será que está realmente prevenindo? Na verdade, longe de prevenir, está produzindo-os em grande quantidade, o que é um grande fato bizarro.<br/>\n<br/>E o problema é que ninguém percebe um assunto tão grave e inacreditável como este.<br/>\n<br/>Neste sentido, chego a pensar que, se não existisse a medicina, os inaptos para o serviço militar sofreriam uma grande e drástica redução.<br/>\n<br/>Não, o fato de que isso é verdade é mais claro do que ver o fogo. O simples fato de que eles aumentam gradualmente à medida que a medicina progride prova isso de forma irrefutável.<br/>\n<br/>O fato vivo de que os inaptos para o serviço militar aumentaram para 200 em cada mil é mais do que suficiente para endossar a minha teoria acima.<br/>\n<br/>Ah, para o futuro da nação, não deve haver nada maior do que isto.<br/>\n<br/>Sendo assim, qual é o erro da medicina, como mencionado acima? Devo expô-lo abertamente.<br/>\n<br/>Ao expô-lo, será necessário esclarecer a partir da essência da doença, que pode ser considerada a raiz desse erro.<br/>\n<br/>E o fato é que o reconhecimento disso na medicina caiu em uma grande ilusão.<br/>\n<br/>Isso porque, na medicina, ainda não está claro por que as doenças ocorrem, e<br/>\n<br/>a visão atual na medicina é a causa passiva de que todos os patógenos são bactérias, ou seja, a teoria da causa externa.<br/>\n<br/>No entanto, este é o erro original.<br/>\n<br/>Não, não é um erro total, mas na verdade é apenas uma solução parcial.<br><br>No entanto, de acordo com a minha pesquisa, a essência da doença é, na verdade, a ação de purificação natural do próprio ser humano.<br/>\n<br/>Ou seja, a teoria da causa interna.<br/>\n<br/>O que é isso? Na sobrevivência humana, devido a várias causas, as impurezas se acumulam constantemente, o que causa a impurificação do sangue, e essa impurificação torna-se a causa da doença.<br/>\n<br/>Mas não é o sangue impuro em si, e sim o próprio trabalho que deve purificar esse sangue impuro.<br/>\n<br/>Portanto, o fenômeno da doença nada mais é do que o sofrimento como ação purificadora.<br/>\n<br/>E por que surgem os pacientes com tuberculose? É porque as impurezas se transformam em sangue impuro e pus e, em qualquer pessoa, acumulam-se nas proximidades do pescoço e dos ombros.<br/>\n<br/>E quando o acúmulo dessas impurezas ultrapassa um certo limite, ocorre a ação de dissolvê-las; o que promove esse motivo é o frio do inverno, e esse trabalho é o resfriado.<br/>\n<br/>Portanto, ao contrair um resfriado, ocorre a febre para dissolver essas impurezas, o pus torna-se ralo e é eliminado como escarro e muco nasal, e com isso o corpo humano consegue manter a saúde.<br/>\n<br/>Portanto, o resfriado é, na verdade, o método mais simples e divino para se livrar de todas as doenças.<br/>\n<br/>No entanto, desde os tempos antigos, diz-se que o resfriado é a causa de todas as doenças, mas isso é um erro total;<br/>\n<br/>na verdade, é o oposto, o melhor método para evitar todas as doenças, sendo um método de preservação da saúde extremamente engenhoso criado pelo Deus Criador.<br/>\n<br/>Apesar disso, a medicina, que é cega a isso, teme muito contrair um resfriado e tenta evitá-lo a todo custo.<br/>\n<br/>Por isso, caso se contraia a doença, teme-se a febre e tenta-se baixá-la a todo custo.<br/>\n<br/>Como resultado, a preciosa purificação torna-se impossível e, por fim, as impurezas permanecem como estão, endurecendo com o passar do tempo.<br/>\n<br/>Esse endurecimento das impurezas é, na verdade, a causa original da debilitação tuberculosa.<br/>\n<br/>E as consolidações de pus aquoso acumuladas nas proximidades do pescoço e dos ombros, embora a febre baixe temporariamente e se obtenha alívio através de antipiréticos, terapia de repouso e outros, isso é temporário e não é a verdadeira cura, de modo que<br/>\n<br/>contrai-se novamente um resfriado devido à ação de purificação natural, mas a medicina realiza novamente a prevenção da purificação e, como resultado, o endurecimento do pus vai se agravando gradualmente.<br/>\n<br/>Ao repetir tais coisas, o endurecimento do pus aumenta cada vez mais, de modo que, como resultado natural, a febre causada pela purificação natural torna-se tão persistente que não se acalma facilmente nem mesmo com antipiréticos.<br/>\n<br/>O pus dissolvido devido a essa febre necessária torna-se escarro e é excretado.<br/>\n<br/>Por causa disso, ocorre a tosse, que se torna contínua.<br><br>Além disso, não se pode ignorar outro sintoma.<br/>\n<br/>É que as impurezas de todo o corpo, que tentam se acumular constantemente nas glândulas cervicais e nos ombros, encontram as consolidações de pus de longa data acumuladas nessas áreas, tornando impossível o acúmulo nessas partes, de modo que<br/>\n<br/>inevitavelmente se acumulam e aderem abaixo disso, desde a parte superior do peito até o periósteo das costelas sob os seios e as axilas.<br/>\n<br/>A razão pela qual a parte de adesão é a área dos seios e axilas é, obviamente, devido à concentração nervosa causada pelo fato de o ser humano usar constantemente ambos os braços.<br/>\n<br/>E como este sintoma é no peito, o diagnóstico médico é de tuberculose pulmonar ou infiltração pulmonar, mas na verdade, neste momento, não há nenhuma anormalidade nos pulmões.<br/>\n<br/>Isso porque o que foi descrito acima não é um sintoma interno das costelas, mas sim externo às costelas.<br/>\n<br/>No entanto, como há febre, estertores e o aparecimento de sombras na radiografia, é compreensível que se diagnostique erroneamente como doença pulmonar, mas isso é totalmente incorreto.<br/>\n<br/>Portanto, vendo que este sintoma, através do meu tratamento, cura-se completamente sem uma única exceção, fica claro que não há anormalidade nos pulmões.<br><br>Em seguida, como causa do agravamento das doenças pulmonares, há especialmente a questão da indigestão.<br/>\n<br/>E não é preciso dizer que a maior parte da causa disso se deve à medicina equivocada.<br/>\n<br/>É que, assim que se sabe que é uma doença pulmonar, a medicina prescreve repouso absoluto.<br/>\n<br/>Por isso, a fraqueza estomacal devido à falta de exercício é notável, e outro fator é fazer tomar remédios para a digestão, mas<br/>\n<br/>na realidade, o resultado é o oposto do objetivo de fortalecer o estômago e aumentar o apetite.<br/>\n<br/>Isso porque, temporariamente, a digestão torna-se vigorosa devido ao remédio para o estômago, mas com o passar dos dias, a força de atividade do próprio estômago declina gradualmente.<br/>\n<br/>Como o medicamento faz a digestão, o estômago não tem necessidade de atividade, sendo uma razão natural que ele se desgaste.<br/>\n<br/>Como resultado, o efeito do remédio para o estômago enfraquece gradualmente e ocorre a perda de apetite, de modo que se faz tomar ainda mais remédio para o estômago; por essa ação cíclica,<br/>\n<br/>o estômago acaba entrando em estado de sono, e o fato de isso agravar a doença é, na verdade, até fatal.<br/>\n<br/>A causa das doenças estomacais, que atualmente estão aumentando em grande número, também pode ser compreendida por isso.<br><br>Além disso, os erros nas causas e tratamentos de diarreia, hemoptise, suores noturnos, etc., são muito semelhantes aos descritos acima, por isso vou omiti-los, mas<br/>\n<br/>em suma, como fica claro pelo exposto acima, a medicina moderna está trilhando um caminho de ilusão surpreendente.<br/>\n<br/>Dizendo isso em uma palavra, assim que ocorre uma doença no corpo humano, o método que tenta curá-la torna-se um obstáculo ao tratamento, e<br/>\n<br/>especialmente o que pode ser chamado de raiz mais fundamental desse obstáculo são os antipiréticos e as compressas de gelo.<br/>\n<br/>Portanto, falando sem reservas, é uma luta entre o trabalho de cura do próprio corpo humano e a medicina que tenta impedir a cura, e o aumento da tuberculose é o resultado disso.<br/>\n<br/>Sendo assim, o que é melhor fazer?<br/>\n<br/>Em primeiro lugar, ao contrair um resfriado, deve-se respeitar a febre e deixá-la como está.<br/>\n<br/>Fazendo isso, as impurezas serão dissolvidas e excretadas favoravelmente, curando-se de forma fundamental e muito favorável, de modo que, naturalmente, a causa predisponente da recaída será eliminada.<br/>\n<br/>Sabe-se que não há um único erro nisso ao se fazer a experiência.<br/>\n<br/>Mesmo vendo por essa razão, saber-se-á que a verdadeira causa do aumento drástico da tuberculose é, sem dúvida, que os antipiréticos são o primeiro passo.<br/>\n<br/>Portanto, não hesito em afirmar que, apenas proibindo os antipiréticos, abolindo o método de compressas de gelo e não prevenindo os resfriados, os pacientes com tuberculose provavelmente diminuirão para menos de um terço.<br/>\n<br/>Na verdade, o fato aterrorizante e inacreditável de que a medicina está criando pacientes com tuberculose está sendo realizado abertamente sob a proteção do Estado.<br/>\n<br/>No entanto, mesmo na medicina, pode-se reconhecer um certo progresso.<br/>\n<br/>Isso é o refinamento das máquinas, a complexidade e variedade dos tratamentos, e a multiplicidade e uso diversificado de medicamentos.<br/>\n<br/>No entanto, enquanto houver ilusão sobre a causa fundamental da doença, eles apenas servem para iludir as pessoas, e<br/>\n<br/>há até o perigo de que, pelo contrário, ao se absorverem e se satisfazerem com eles, acabem se afastando do fundamental.<br/>\n<br/>Por isso, se houver a descoberta definitiva da causa da doença, os instrumentos e medicamentos se tornarão existências desnecessárias.<br><br>Em seguida, o fato de haver muitos erros nos diagnósticos médicos atuais é algo realmente surpreendente.<br/>\n<br/>Ao examinar, vejo que mesmo os diagnósticos nos grandes hospitais governamentais são, em quase setenta ou oitenta por cento, diagnósticos errôneos.<br/>\n<br/>As pessoas que lerem isso não conseguirão acreditar, mas os fatos são rigorosos e não podem ser alterados.<br/>\n<br/>Isso ocorre porque mesmo a radiografia, que é o único método de diagnóstico na medicina, não é de forma alguma precisa.<br/>\n<br/>Isso também fica claro pelo fato de que as consolidações de pus acumuladas nas costelas e no seu exterior, mencionadas anteriormente, e o pus não consolidado, que aparecem como sombras, são confundidos com doenças pulmonares.<br/>\n<br/>É claro que isso deve ser porque a imagem fotográfica é plana, mas também há necessidade de uma grande conscientização sobre isso.<br/>\n<br/>Além disso, quanto aos estertores, há casos em que são nos alvéolos pulmonares, mas também há muitos casos em que são causados pelo pus aquoso perto das costelas, como mencionado acima.<br/>\n<br/>Também é preciso saber que, mesmo que haja estertores nos alvéolos pulmonares, há muitos casos em que não é doença pulmonar.<br/>\n<br/>Além disso, quanto à febrícula, em quase todos os casos, a causa não é os pulmões nem em uma em cada dez pessoas.<br/>\n<br/>A maioria é nas glândulas cervicais e ombros, costelas, estômago, abdômen, região lombar, etc.<br/>\n<br/>Ao me basear nessas descobertas, o fato de o diagnóstico médico ser tão infantil chega a ser incompreensível.<br/>\n<br/>Portanto, atualmente, a maioria dos pacientes que são diagnosticados com tuberculose pulmonar e estão pessimistas, na verdade, podem ser chamados de pacientes pulmonares sem anormalidades nos pulmões, e eu sempre rio disso.<br/>\n<br/>A taxa de cura das doenças pulmonares que eu estou tratando, apesar de todos eles serem apenas casos difíceis e complicados que não se curaram mesmo recebendo todos os tratamentos médicos,<br/>\n<br/>está atingindo resultados de cura de mais de oitenta por cento; se perguntarem por que isso acontece, é porque eles são os chamados pacientes pulmonares sem anormalidades nos pulmões.<br/>　<br/>\n<br/>Em seguida, apontarei outro tratamento errôneo. É que não há distinção entre melhora da doença e cura, confundindo-as.<br/>\n<br/>Para começar, como a doença é uma ação purificadora, como mencionado anteriormente, os vários sofrimentos como febre, tosse, escarro, hemoptise, suores noturnos, etc.,<br/>\n<br/>quanto mais vigorosa for a vitalidade do paciente, mais violentos devem ser os fenômenos de sofrimento.<br/>\n<br/>No entanto, nesse caso, a medicina realiza frequentemente tratamentos sintomáticos para aliviar o sofrimento.<br/>\n<br/>Esses tratamentos são medicamentos, alimentos nutritivos de origem animal, método de repouso absoluto, etc.<br/>\n<br/>No entanto, como os primeiros turvam o sangue e os últimos desgastam a vitalidade de todo o corpo, é natural que a força purificadora enfraqueça.<br/>\n<br/>Como resultado, a febre baixa, a tosse e o escarro diminuem, de modo que os sintomas da doença certamente melhoram e parecem caminhar para a cura, e às vezes chega-se a pensar que está quase curado.<br/>\n<br/>Mas mal sabem que isso é um alívio temporário devido à paralisação da purificação e não é cura, de modo que ocorre recaída ou mantém-se o estado atual, prolongando-se por vários anos sem curar completamente nem piorar, e todos sabem que há muitos pacientes assim.<br/>\n<br/>Como isso é totalmente a prevenção da cura natural, se o paciente fizer exercícios durante esse processo, a força purificadora surgirá imediatamente e ele terá febre.<br/>\n<br/>Os médicos se assustam com isso, interpretam erroneamente como agravamento da doença e mandam parar. O fato de ter surgido recentemente no Ocidente a teoria de que se deve tratar a tuberculose enquanto se trabalha é a prova de que despertaram para o erro desse repouso absoluto.<br><br>Ao sintetizar a imprecisão do diagnóstico, a ilusão sobre a causa da doença e os erros nos métodos de tratamento, como exposto acima, a menos que a medicina moderna faça uma grande revolução, a perda para a nação e a infelicidade do povo serão incalculáveis.<br/>\n<br/>Ao compreender plenamente esta verdade, haverá alguém que não sinta calafrios?<br/>\n<br/>Aqui, não podemos deixar de soar um grande alarme e incitar um grande despertar nas partes interessadas.<br/>\n<br/>Acredito que o título \"A Medicina Retrocedeu?\" fica claro com isso.\" (Extraído do livro SHIN NIHON IJUTSUSHO) <hr/>\n<br/>\n<br/>",
                    "publication_title_pt": "",
                    "title_ptbr": "Resfriado e Tuberculose　３",
                    "title_ja": "明主様御教え　「医学は退歩したか」"
                },
                {
                    "title": "風邪と結核　３",
                    "date": "昭和27年1月15日",
                    "content": "<b><font size=\"+2\">明主様御垂示　「淋巴腺は毒素の掃き溜め」</font></b>　（昭和27年1月15日） <b><font color=\"#990000\" size=\"+1\">信者の質問</font></b><br/>「淋巴の機能と血液および毒素との関係につき御教えをお願い申し上げます。<br/>\n<br/>心臓と肝臓というような密接な関係があるように想像されますが。」<br><br>\n<b><font color=\"#0000ff\" size=\"+1\">明主様御垂示</font></b><br/>「心臓と肝臓というような関係とは違いますがね。<br/>\n<br/>つまり、頭脳とか特に使うから神経が集中するでしょう。<br/>\n<br/>淋巴腺というのは、毒素の集まり場所なんです。つまりハキ溜めなんです。<br/>\n<br/>風邪を引くと熱が出るでしょう。<br/>\n<br/>横から前の方は痰になって出る。<br/>\n<br/>といって、ここからすぐ出るんじゃないですよ。<br/>\n<br/>いったん肺に行って、それから痰になって出るんです。<br/>\n<br/>つまり、毒素が一時的溜まる機関ですね。<br/>\n<br/>それから・・・出てしまえば良いですが、ここに出ないようにいろんなことをして固めますね。<br/>\n<br/>それが瘰癧（るいれき）です。瘰癧というと、固く引っ込むようになりますね。<br/>\n<br/>あれは、人間が作ったんです。<br/>\n<br/>だから、実に風邪というのは結構なものなんです。<br/>\n<br/>風邪を引くと熱が出て、痰や洟（はな）が出るでしょう。<br/>\n<br/>そうすると、人間はいつも健康でいられるんです。<br/>\n<br/>それを、固めるから、しつこくて \n・・・肺の中に固める・・・それで結核を作っているんですね。<br/>\n<br/>あれは、実にうまく結核を作ってますよ。<br/>\n<br/>あれは、よほど研究しなければね。<br/>\n<br/>医学が病気を作る研究は、実に進歩してます。 ですから、その犠牲になった人間は、実にかわいそうなものですよ。」 <p align=\"center\"><br><br>\n<br><br>\n<br><br>\n<br><br>\n </p>\n</blockquote>\n</blockquote>\n</blockquote>\n</body>",
                    "filename": "kaze3K.html",
                    "title_pt": "Resfriado e Tuberculose　３",
                    "content_pt": "<b><font size=\"+2\">Palavras de Luz de Meishu-Sama: \"As Glândulas Linfáticas são o Depósito de Toxinas\"</font></b> (15 de janeiro de 1952) <b><font color=\"#990000\" size=\"+1\">Pergunta do fiel</font></b><br/>\"Gostaria de pedir Seus ensinamentos sobre a relação entre a função da linfa, o sangue e as toxinas.<br/>\n<br/>Imagino que haja uma relação íntima como a do coração e do fígado.\"<br><br>\n<b><font color=\"#0000ff\" size=\"+1\">Palavras de Luz de Meishu-Sama</font></b><br/>\"É diferente de uma relação como a do coração e do fígado.<br/>\n<br/>Ou seja, como se usa muito o cérebro, os nervos se concentram, não é?<br/>\n<br/>As glândulas linfáticas são o local de encontro das toxinas. Ou seja, são um depósito.<br/>\n<br/>Quando se pega um resfriado, tem-se febre, não é?<br/>\n<br/>A parte dos lados para a frente sai em forma de escarro.<br/>\n<br/>Mas isso não quer dizer que sai logo daqui.<br/>\n<br/>Vai primeiro para os pulmões e depois sai em forma de escarro.<br/>\n<br/>Ou seja, é um órgão onde as toxinas se acumulam temporariamente.<br/>\n<br/>E então... se sair, tudo bem, mas fazem várias coisas para não deixar sair e endurecem, não é?<br/>\n<br/>Isso é a escrófula. Quando se fala em escrófula, ela fica dura e retraída, não é?<br/>\n<br/>Aquilo foi o ser humano que criou.<br/>\n<br/>Por isso, o resfriado é realmente uma coisa maravilhosa.<br/>\n<br/>Quando se pega um resfriado, tem-se febre, sai escarro e muco nasal, não é?<br/>\n<br/>Fazendo isso, o ser humano pode estar sempre saudável.<br/>\n<br/>Como endurecem isso, fica persistente... endurecem dentro dos pulmões... e com isso estão criando a tuberculose.<br/>\n<br/>Eles criam a tuberculose muito bem.<br/>\n<br/>Isso exige muita pesquisa.<br/>\n<br/>A pesquisa da medicina para criar doenças está realmente avançada. Por isso, os seres humanos que se tornaram vítimas disso são realmente dignos de pena.\" <p align=\"center\"><br><br>\n<br><br>\n<br><br>\n<br><br>\n </p>\n</blockquote>\n</blockquote>\n</blockquote>\n</body>",
                    "publication_title_pt": "",
                    "title_ptbr": "Resfriado e Tuberculose　３",
                    "title_ja": "明主様御垂示　「淋巴腺は毒素の掃き溜め」"
                }
            ]
        }
    ]
}